Metadata-Version: 2.1
Name: vnmapping
Version: 1.0.12
Summary: demo
Author: ZZL
Author-email: test@163.com
Requires-Python: >=3.6
License-File: LICENSE
